LICENSE
MANIFEST.in
README.md
setup.py
cqlsl/__init__.py
cqlsl/sessions.py
cqlsl/utils.py
cqlsl.egg-info/PKG-INFO
cqlsl.egg-info/SOURCES.txt
cqlsl.egg-info/dependency_links.txt
cqlsl.egg-info/requires.txt
cqlsl.egg-info/top_level.txt
cqlsl/statements/__init__.py
cqlsl/statements/base.py
cqlsl/statements/delete.py
cqlsl/statements/insert.py
cqlsl/statements/select.py
cqlsl/statements/update.py