Metadata-Version: 1.1
Name: cqlsl
Version: 0.2.0
Summary: CQL for Python without any additional abstraction layers
Home-page: https://github.com/drudim/cqlsl
Author: Dmytro Popovych
Author-email: drudim.ua@gmail.com
License: MIT
Keywords: cassandra,cql
Platform: UNKNOWN
Classifier: Development Status :: 4 - Beta
Classifier: Intended Audience :: Developers
Classifier: License :: OSI Approved :: MIT License
Classifier: Programming Language :: Python :: 2.7
Classifier: Programming Language :: Python :: 3.4
Classifier: Topic :: Database :: Front-Ends
Classifier: Operating System :: OS Independent
